django_geo_db/widgets.py
django_geo_db/autocomplete_urls.py
django_geo_db/settings.py
django_geo_db/__init__.py
django_geo_db/models.py
django_geo_db/services.py
django_geo_db/urls.py
django_geo_db/context_processors.py
django_geo_db/forms.py
django_geo_db/serializers.py
django_geo_db/utilities.py
django_geo_db/apps.py
django_geo_db/views.py
django_geo_db/managers.py
django_geo_db/autocomplete_views.py
django_geo_db/admin.py
django_geo_db/sql/django_geo_db_geocoordinate.sql
django_geo_db/sql/django_geo_db_continent.sql
django_geo_db/sql/django_geo_db_location.sql
django_geo_db/sql/django_geo_db_zipcode.sql
django_geo_db/sql/django_geo_db_state.sql
django_geo_db/sql/django_geo_db_city.sql
django_geo_db/sql/django_geo_db_country.sql
django_geo_db/scripts/drop_then_add_geo.sh
django_geo_db/scripts/dump_geo_tables.sh
django_geo_db/static/js/django_geo_db/utilities.js.map
django_geo_db/static/js/django_geo_db/utilities.js
django_geo_db/migrations/0001_initial.py
django_geo_db/migrations/__init__.py
django_geo_db/management/__init__.py
django_geo_db/management/commands/generate_names.py
django_geo_db/management/commands/__init__.py
django_geo_db/management/commands/resave_all_geocoordinates.py
django_geo_db/management/commands/setup_us_data.py
django_geo_db/data/__init__.py
django_geo_db/data/us-states.csv
django_geo_db/data/us-cities-and-zips.csv
django_geo_db/data/countries.csv
django_geo_db/templates/django_geo_db/geocoordinate.html
django_geo_db/templates/django_geo_db/location.html
django_geo_db/templatetags/__init__.py
django_geo_db/tests/__init__.py
django_geo_db/tests/test_geoCoordinate.py
django_geo_db-0.1.16.dist-info/RECORD
django_geo_db-0.1.16.dist-info/top_level.txt
django_geo_db-0.1.16.dist-info/metadata.json
django_geo_db-0.1.16.dist-info/WHEEL
django_geo_db-0.1.16.dist-info/METADATA
django_geo_db-0.1.16.dist-info/DESCRIPTION.rst
